Metadata-Version: 1.0
Name: jlim-distributions
Version: 0.1
Summary: Gaussian and Binomial Distributions
Home-page: UNKNOWN
Author: UNKNOWN
Author-email: UNKNOWN
License: UNKNOWN
Platform: UNKNOWN
